spurelations/__init__.py
spurelations/main.py
spurelations-0.1.1.dist-info/LICENSE
spurelations-0.1.1.dist-info/METADATA
spurelations-0.1.1.dist-info/WHEEL
spurelations-0.1.1.dist-info/entry_points.txt
spurelations-0.1.1.dist-info/top_level.txt
spurelations-0.1.1.dist-info/RECORD
