Metadata-Version: 2.1
Name: spurelations
Version: 0.1.1
Summary: Download spurious correlations from tylervigen.com
Author-email: tcsenpai <tcsenpai@discus.sh>
License: MIT License
Project-URL: Homepage, https://github.com/tcsenpai/spurelations
Project-URL: Repository, https://github.com/tcsenpai/spurelations.git
Keywords: spurious,correlations,data,visualization
Classifier: Programming Language :: Python :: 3
Classifier: License :: OSI Approved :: MIT License
Classifier: Operating System :: OS Independent
Requires-Python: >=3.7
License-File: LICENSE
Requires-Dist: beautifulsoup4
Requires-Dist: requests
Requires-Dist: tqdm
Requires-Dist: colorama
